bnop/__init__.py
bnop/bnop_facades.py
bnop/bnop_io/__init__.py
bnop/bnop_io/shelve_bnop.py
bnop/core/__init__.py
bnop/core/factories/__init__.py
bnop/core/factories/bnop_element_factories.py
bnop/core/factories/bnop_name_factories.py
bnop/core/factories/bnop_object_factories.py
bnop/core/factories/bnop_placeabletype_factories.py
bnop/core/factories/bnop_tuple_factories.py
bnop/core/factories/bnop_type_factories.py
bnop/core/factories/bnop_type_place_factories.py
bnop/core/object_model/__init__.py
bnop/core/object_model/bnop_repositories.py
bnop/core/object_model/objects/__init__.py
bnop/core/object_model/objects/bnop_elements.py
bnop/core/object_model/objects/bnop_names.py
bnop/core/object_model/objects/bnop_objects.py
bnop/core/object_model/objects/bnop_placeable_types.py
bnop/core/object_model/objects/bnop_representations.py
bnop/core/object_model/objects/bnop_tuples.py
bnop/core/object_model/objects/bnop_type_places.py
bnop/core/object_model/objects/bnop_types.py
bnop/core/object_model/objects/places/__init__.py
bnop/core/object_model/objects/places/bnop_placed_objects_dictionaries.py
bnop/core/object_model/objects/places/bnop_placed_types_dictionaries.py
bnop/infrastructure/__init__.py
bnop/infrastructure/names.py
bnop/infrastructure/translators.py
bnop/mappings/__init__.py
bnop/mappings/boro_object_ckid_mappings.py
bnop/migrations/__init__.py
bnop/migrations/bnop_to_xml_migration/__init__.py
bnop/migrations/bnop_to_xml_migration/adders/__init__.py
bnop/migrations/bnop_to_xml_migration/adders/bnop_name_xml_adder.py
bnop/migrations/bnop_to_xml_migration/adders/bnop_object_xml_adder.py
bnop/migrations/bnop_to_xml_migration/adders/bnop_xml_named_objects_adder.py
bnop/migrations/bnop_to_xml_migration/adders/bnop_xml_names_adder.py
bnop/migrations/bnop_to_xml_migration/bnop_xml_write_orchestrator.py
bnop/migrations/bnop_to_xml_migration/common_knowledge/__init__.py
bnop/migrations/bnop_to_xml_migration/common_knowledge/bnop_to_xml_migration_configurations.py
ontoledgy_bnop-0.1.1.dist-info/LICENSE.md
ontoledgy_bnop-0.1.1.dist-info/METADATA
ontoledgy_bnop-0.1.1.dist-info/WHEEL
ontoledgy_bnop-0.1.1.dist-info/RECORD
