Metadata-Version: 2.1
Name: ontoledgy-bnop
Version: 0.1.1
Summary: a common top level ontology for bCLEARer based on BORO.
Author: Mesbah Khan
Author-email: khanm@ontoledgy.io
Requires-Python: >=3.12,<4.0
Classifier: Programming Language :: Python :: 3
Classifier: Programming Language :: Python :: 3.12
